leapfrogai/__init__.py
leapfrogai/cli.py
leapfrogai/config.py
leapfrogai/errors.py
leapfrogai/llm.py
leapfrogai/serve.py
leapfrogai/utils.py
leapfrogai/audio/audio_pb2.py
leapfrogai/audio/audio_pb2.pyi
leapfrogai/audio/audio_pb2_grpc.py
leapfrogai/chat/chat_pb2.py
leapfrogai/chat/chat_pb2.pyi
leapfrogai/chat/chat_pb2_grpc.py
leapfrogai/completion/completion_pb2.py
leapfrogai/completion/completion_pb2.pyi
leapfrogai/completion/completion_pb2_grpc.py
leapfrogai/embeddings/embeddings_pb2.py
leapfrogai/embeddings/embeddings_pb2.pyi
leapfrogai/embeddings/embeddings_pb2_grpc.py
leapfrogai/name/name_pb2.py
leapfrogai/name/name_pb2.pyi
leapfrogai/name/name_pb2_grpc.py
leapfrogai-0.4.0.dist-info/METADATA
leapfrogai-0.4.0.dist-info/WHEEL
leapfrogai-0.4.0.dist-info/entry_points.txt
leapfrogai-0.4.0.dist-info/licenses/LICENSE
leapfrogai-0.4.0.dist-info/RECORD
