Metadata-Version: 2.1
Name: leapfrogai
Version: 0.4.0
Summary: A tool for building gRPC-based model backends for LeapfrogAI
Author-email: LeapfrogAI Authors <ai@defenseunicorns.com>
License:                                  Apache License
License-File: LICENSE
Classifier: Development Status :: 3 - Alpha
Classifier: License :: OSI Approved :: Apache Software License
Classifier: Operating System :: OS Independent
Classifier: Programming Language :: Python :: 3
Classifier: Topic :: Scientific/Engineering :: Artificial Intelligence
Requires-Python: <3.12,>=3.10
Requires-Dist: click>=8.1.7
Requires-Dist: confz>=2.0.1
Requires-Dist: grpcio-health-checking>=1.58.0
Requires-Dist: grpcio-reflection>=1.58.0
Requires-Dist: grpcio>=1.56.0
Requires-Dist: protobuf>=4.23.3
Requires-Dist: pydantic<2
Provides-Extra: build
Requires-Dist: build; extra == 'build'
Requires-Dist: hatchling; extra == 'build'
Requires-Dist: twine; extra == 'build'
Provides-Extra: tests
Requires-Dist: pytest; extra == 'tests'
